clamera/__init__.py
clamera/camera.py
Clamera-0.1.0.dist-info/METADATA
Clamera-0.1.0.dist-info/WHEEL
Clamera-0.1.0.dist-info/top_level.txt
Clamera-0.1.0.dist-info/RECORD
